cmip6d/__init__.py
cmip6d/cmip6d.py
cmip6d-1.1.dist-info/METADATA
cmip6d-1.1.dist-info/WHEEL
cmip6d-1.1.dist-info/top_level.txt
cmip6d-1.1.dist-info/RECORD
