Metadata-Version: 2.1
Name: cmip6d
Version: 1.1
Summary: A package to download NASA NEX/GDDP-CMIP6 downscaled climate change scenarios
Home-page: https://github.com/jonathanqv/cmip6d
Author: Jonathan Quiroz
Author-email: jonathanqv1@gmail.com
License: MIT license
Requires-Dist: beautifulsoup4
